raydium/__init__.py
raydium/utils/create_close_account.py
raydium/utils/dexscreener.py
raydium-2.1.6.dist-info/METADATA
raydium-2.1.6.dist-info/WHEEL
raydium-2.1.6.dist-info/RECORD
