Metadata-Version: 2.1
Name: raydium
Version: 2.1.6
Summary: Easily buy and sell SPL tokens on Solana's Raydium DEX
Author: SapphireX
Requires-Python: >=3.10,<4.0
Classifier: Programming Language :: Python :: 3
Classifier: Programming Language :: Python :: 3.10
Classifier: Programming Language :: Python :: 3.11
Classifier: Programming Language :: Python :: 3.12
Requires-Dist: base58 (>=2.1.1,<3.0.0)
Requires-Dist: borsh-construct (>=0.1.0,<0.2.0)
Requires-Dist: requests (>=2.32.2,<3.0.0)
Requires-Dist: sol-structs (>=1.0.2,<2.0.0)
Requires-Dist: solana (>=0.34.0,<0.35.0)
Requires-Dist: solders (>=0.21.0,<0.22.0)
Requires-Dist: websockets (>=9.1,<10.0)
